CHANGELOG.rst
LICENSE
MANIFEST.in
README.rst
setup.cfg
setup.py
src/kids/__init__.py
src/kids.cfg.egg-info/PKG-INFO
src/kids.cfg.egg-info/SOURCES.txt
src/kids.cfg.egg-info/dependency_links.txt
src/kids.cfg.egg-info/requires.txt
src/kids.cfg.egg-info/top_level.txt
src/kids/cfg/__init__.py